{
  "bomFormat": "CycloneDX",
  "specVersion": "1.5",
  "serialNumber": "urn:uuid:5d229b7b-ac43-459d-a245-bff5545925f2",
  "version": 1,
  "metadata": {
    "timestamp": "2025-07-21T13:27:56Z",
    "tools": {
      "components": [
        {
          "type": "application",
          "author": "Amazon Web Services, Inc. (AWS)",
          "name": "inspector-sbomgen",
          "version": "1.8.0",
          "hashes": [
            {
              "alg": "SHA-256",
              "content": "SAMPLE_SHA256_HASH_PLACEHOLDER_REPLACE_WITH_ACTUAL_HASH"
            }
          ]
        }
      ]
    },
    "component": {
      "bom-ref": "comp-1",
      "type": "file",
      "name": "/home/ec2-user/simple-node-app"
    }
  },
  "components": [
    {
      "bom-ref": "comp-2",
      "type": "library",
      "name": "depd",
      "version": "2.0.0",
      "purl": "pkg:npm/depd@2.0.0",
      "properties": [
        {
          "name": "amazon:inspector:sbom_generator:source_path",
          "value": "/home/ec2-user/simple-node-app/node_modules/depd/package.json"
        }
      ]
    },
    {
      "bom-ref": "comp-3",
      "type": "library",
      "name": "toidentifier",
      "version": "1.0.1",
      "purl": "pkg:npm/toidentifier@1.0.1",
      "properties": [
        {
          "name": "amazon:inspector:sbom_generator:source_path",
          "value": "/home/ec2-user/simple-node-app/node_modules/toidentifier/package.json"
        }
      ]
    },
    {
      "bom-ref": "comp-4",
      "type": "library",
      "name": "ms",
      "version": "2.0.0",
      "purl": "pkg:npm/ms@2.0.0",
      "properties": [
        {
          "name": "amazon:inspector:sbom_generator:source_path",
          "value": "/home/ec2-user/simple-node-app/node_modules/ms/package.json"
        }
      ]
    },
    {
      "bom-ref": "comp-5",
      "type": "library",
      "name": "escape-html",
      "version": "1.0.3",
      "purl": "pkg:npm/escape-html@1.0.3",
      "properties": [
        {
          "name": "amazon:inspector:sbom_generator:source_path",
          "value": "/home/ec2-user/simple-node-app/node_modules/escape-html/package.json"
        }
      ]
    },
    {
      "bom-ref": "comp-6",
      "type": "library",
      "name": "on-finished",
      "version": "2.4.1",
      "purl": "pkg:npm/on-finished@2.4.1",
      "properties": [
        {
          "name": "amazon:inspector:sbom_generator:source_path",
          "value": "/home/ec2-user/simple-node-app/node_modules/on-finished/package.json"
        }
      ]
    },
    {
      "bom-ref": "comp-7",
      "type": "library",
      "name": "hasown",
      "version": "2.0.2",
      "purl": "pkg:npm/hasown@2.0.2",
      "properties": [
        {
          "name": "amazon:inspector:sbom_generator:source_path",
          "value": "/home/ec2-user/simple-node-app/node_modules/hasown/package.json"
        }
      ]
    },
    {
      "bom-ref": "comp-8",
      "type": "library",
      "name": "object-inspect",
      "version": "1.13.4",
      "purl": "pkg:npm/object-inspect@1.13.4",
      "properties": [
        {
          "name": "amazon:inspector:sbom_generator:source_path",
          "value": "/home/ec2-user/simple-node-app/node_modules/object-inspect/package.json"
        }
      ]
    },
    {
      "bom-ref": "comp-9",
      "type": "library",
      "name": "chokidar",
      "version": "3.6.0",
      "purl": "pkg:npm/chokidar@3.6.0",
      "properties": [
        {
          "name": "amazon:inspector:sbom_generator:source_path",
          "value": "/home/ec2-user/simple-node-app/node_modules/chokidar/package.json"
        }
      ]
    },
    {
      "bom-ref": "comp-10",
      "type": "library",
      "name": "range-parser",
      "version": "1.2.1",
      "purl": "pkg:npm/range-parser@1.2.1",
      "properties": [
        {
          "name": "amazon:inspector:sbom_generator:source_path",
          "value": "/home/ec2-user/simple-node-app/node_modules/range-parser/package.json"
        }
      ]
    },
    {
      "bom-ref": "comp-11",
      "type": "library",
      "name": "is-glob",
      "version": "4.0.3",
      "purl": "pkg:npm/is-glob@4.0.3",
      "properties": [
        {
          "name": "amazon:inspector:sbom_generator:source_path",
          "value": "/home/ec2-user/simple-node-app/node_modules/is-glob/package.json"
        }
      ]
    },
    {
      "bom-ref": "comp-12",
      "type": "library",
      "name": "minimatch",
      "version": "3.1.2",
      "purl": "pkg:npm/minimatch@3.1.2",
      "properties": [
        {
          "name": "amazon:inspector:sbom_generator:source_path",
          "value": "/home/ec2-user/simple-node-app/node_modules/minimatch/package.json"
        }
      ]
    },
    {
      "bom-ref": "comp-13",
      "type": "library",
      "name": "es-errors",
      "version": "1.3.0",
      "purl": "pkg:npm/es-errors@1.3.0",
      "properties": [
        {
          "name": "amazon:inspector:sbom_generator:source_path",
          "value": "/home/ec2-user/simple-node-app/node_modules/es-errors/package.json"
        }
      ]
    },
    {
      "bom-ref": "comp-14",
      "type": "library",
      "name": "body-parser",
      "version": "1.20.3",
      "purl": "pkg:npm/body-parser@1.20.3",
      "properties": [
        {
          "name": "amazon:inspector:sbom_generator:source_path",
          "value": "/home/ec2-user/simple-node-app/node_modules/body-parser/package.json"
        }
      ]
    },
    {
      "bom-ref": "comp-15",
      "type": "library",
      "name": "bytes",
      "version": "3.1.2",
      "purl": "pkg:npm/bytes@3.1.2",
      "properties": [
        {
          "name": "amazon:inspector:sbom_generator:source_path",
          "value": "/home/ec2-user/simple-node-app/node_modules/bytes/package.json"
        }
      ]
    },
    {
      "bom-ref": "comp-16",
      "type": "library",
      "name": "gopd",
      "version": "1.2.0",
      "purl": "pkg:npm/gopd@1.2.0",
      "properties": [
        {
          "name": "amazon:inspector:sbom_generator:source_path",
          "value": "/home/ec2-user/simple-node-app/node_modules/gopd/package.json"
        }
      ]
    },
    {
      "bom-ref": "comp-17",
      "type": "library",
      "name": "send",
      "version": "0.19.0",
      "purl": "pkg:npm/send@0.19.0",
      "properties": [
        {
          "name": "amazon:inspector:sbom_generator:source_path",
          "value": "/home/ec2-user/simple-node-app/node_modules/send/package.json"
        }
      ]
    },
    {
      "bom-ref": "comp-18",
      "type": "library",
      "name": "content-type",
      "version": "1.0.5",
      "purl": "pkg:npm/content-type@1.0.5",
      "properties": [
        {
          "name": "amazon:inspector:sbom_generator:source_path",
          "value": "/home/ec2-user/simple-node-app/node_modules/content-type/package.json"
        }
      ]
    },
    {
      "bom-ref": "comp-19",
      "type": "library",
      "name": "ipaddr.js",
      "version": "1.9.1",
      "purl": "pkg:npm/ipaddr.js@1.9.1",
      "properties": [
        {
          "name": "amazon:inspector:sbom_generator:source_path",
          "value": "/home/ec2-user/simple-node-app/node_modules/ipaddr.js/package.json"
        }
      ]
    },
    {
      "bom-ref": "comp-20",
      "type": "library",
      "name": "qs",
      "version": "6.13.0",
      "purl": "pkg:npm/qs@6.13.0",
      "properties": [
        {
          "name": "amazon:inspector:sbom_generator:source_path",
          "value": "/home/ec2-user/simple-node-app/node_modules/qs/package.json"
        }
      ]
    },
    {
      "bom-ref": "comp-21",
      "type": "library",
      "name": "side-channel-map",
      "version": "1.0.1",
      "purl": "pkg:npm/side-channel-map@1.0.1",
      "properties": [
        {
          "name": "amazon:inspector:sbom_generator:source_path",
          "value": "/home/ec2-user/simple-node-app/node_modules/side-channel-map/package.json"
        }
      ]
    },
    {
      "bom-ref": "comp-22",
      "type": "library",
      "name": "side-channel",
      "version": "1.1.0",
      "purl": "pkg:npm/side-channel@1.1.0",
      "properties": [
        {
          "name": "amazon:inspector:sbom_generator:source_path",
          "value": "/home/ec2-user/simple-node-app/node_modules/side-channel/package.json"
        }
      ]
    },
    {
      "bom-ref": "comp-23",
      "type": "library",
      "name": "http-errors",
      "version": "2.0.0",
      "purl": "pkg:npm/http-errors@2.0.0",
      "properties": [
        {
          "name": "amazon:inspector:sbom_generator:source_path",
          "value": "/home/ec2-user/simple-node-app/node_modules/http-errors/package.json"
        }
      ]
    },
    {
      "bom-ref": "comp-24",
      "type": "library",
      "name": "es-object-atoms",
      "version": "1.1.1",
      "purl": "pkg:npm/es-object-atoms@1.1.1",
      "properties": [
        {
          "name": "amazon:inspector:sbom_generator:source_path",
          "value": "/home/ec2-user/simple-node-app/node_modules/es-object-atoms/package.json"
        }
      ]
    },
    {
      "bom-ref": "comp-25",
      "type": "library",
      "name": "nodemon",
      "version": "3.1.10",
      "purl": "pkg:npm/nodemon@3.1.10",
      "properties": [
        {
          "name": "amazon:inspector:sbom_generator:source_path",
          "value": "/home/ec2-user/simple-node-app/node_modules/nodemon/package.json"
        }
      ]
    },
    {
      "bom-ref": "comp-26",
      "type": "library",
      "name": "pstree.remy",
      "version": "1.1.8",
      "purl": "pkg:npm/pstree.remy@1.1.8",
      "properties": [
        {
          "name": "amazon:inspector:sbom_generator:source_path",
          "value": "/home/ec2-user/simple-node-app/node_modules/pstree.remy/package.json"
        }
      ]
    },
    {
      "bom-ref": "comp-27",
      "type": "library",
      "name": "inherits",
      "version": "2.0.4",
      "purl": "pkg:npm/inherits@2.0.4",
      "properties": [
        {
          "name": "amazon:inspector:sbom_generator:source_path",
          "value": "/home/ec2-user/simple-node-app/node_modules/inherits/package.json"
        }
      ]
    },
    {
      "bom-ref": "comp-28",
      "type": "library",
      "name": "mime-db",
      "version": "1.52.0",
      "purl": "pkg:npm/mime-db@1.52.0",
      "properties": [
        {
          "name": "amazon:inspector:sbom_generator:source_path",
          "value": "/home/ec2-user/simple-node-app/node_modules/mime-db/package.json"
        }
      ]
    },
    {
      "bom-ref": "comp-29",
      "type": "library",
      "name": "side-channel-weakmap",
      "version": "1.0.2",
      "purl": "pkg:npm/side-channel-weakmap@1.0.2",
      "properties": [
        {
          "name": "amazon:inspector:sbom_generator:source_path",
          "value": "/home/ec2-user/simple-node-app/node_modules/side-channel-weakmap/package.json"
        }
      ]
    },
    {
      "bom-ref": "comp-30",
      "type": "library",
      "name": "safer-buffer",
      "version": "2.1.2",
      "purl": "pkg:npm/safer-buffer@2.1.2",
      "properties": [
        {
          "name": "amazon:inspector:sbom_generator:source_path",
          "value": "/home/ec2-user/simple-node-app/node_modules/safer-buffer/package.json"
        }
      ]
    },
    {
      "bom-ref": "comp-31",
      "type": "library",
      "name": "is-number",
      "version": "7.0.0",
      "purl": "pkg:npm/is-number@7.0.0",
      "properties": [
        {
          "name": "amazon:inspector:sbom_generator:source_path",
          "value": "/home/ec2-user/simple-node-app/node_modules/is-number/package.json"
        }
      ]
    },
    {
      "bom-ref": "comp-32",
      "type": "library",
      "name": "array-flatten",
      "version": "1.1.1",
      "purl": "pkg:npm/array-flatten@1.1.1",
      "properties": [
        {
          "name": "amazon:inspector:sbom_generator:source_path",
          "value": "/home/ec2-user/simple-node-app/node_modules/array-flatten/package.json"
        }
      ]
    },
    {
      "bom-ref": "comp-33",
      "type": "library",
      "name": "picomatch",
      "version": "2.3.1",
      "purl": "pkg:npm/picomatch@2.3.1",
      "properties": [
        {
          "name": "amazon:inspector:sbom_generator:source_path",
          "value": "/home/ec2-user/simple-node-app/node_modules/picomatch/package.json"
        }
      ]
    },
    {
      "bom-ref": "comp-34",
      "type": "library",
      "name": "encodeurl",
      "version": "2.0.0",
      "purl": "pkg:npm/encodeurl@2.0.0",
      "properties": [
        {
          "name": "amazon:inspector:sbom_generator:source_path",
          "value": "/home/ec2-user/simple-node-app/node_modules/encodeurl/package.json"
        }
      ]
    },
    {
      "bom-ref": "comp-35",
      "type": "library",
      "name": "readdirp",
      "version": "3.6.0",
      "purl": "pkg:npm/readdirp@3.6.0",
      "properties": [
        {
          "name": "amazon:inspector:sbom_generator:source_path",
          "value": "/home/ec2-user/simple-node-app/node_modules/readdirp/package.json"
        }
      ]
    },
    {
      "bom-ref": "comp-36",
      "type": "library",
      "name": "methods",
      "version": "1.1.2",
      "purl": "pkg:npm/methods@1.1.2",
      "properties": [
        {
          "name": "amazon:inspector:sbom_generator:source_path",
          "value": "/home/ec2-user/simple-node-app/node_modules/methods/package.json"
        }
      ]
    },
    {
      "bom-ref": "comp-37",
      "type": "library",
      "name": "binary-extensions",
      "version": "2.3.0",
      "purl": "pkg:npm/binary-extensions@2.3.0",
      "properties": [
        {
          "name": "amazon:inspector:sbom_generator:source_path",
          "value": "/home/ec2-user/simple-node-app/node_modules/binary-extensions/package.json"
        }
      ]
    },
    {
      "bom-ref": "comp-38",
      "type": "library",
      "name": "accepts",
      "version": "1.3.8",
      "purl": "pkg:npm/accepts@1.3.8",
      "properties": [
        {
          "name": "amazon:inspector:sbom_generator:source_path",
          "value": "/home/ec2-user/simple-node-app/node_modules/accepts/package.json"
        }
      ]
    },
    {
      "bom-ref": "comp-39",
      "type": "library",
      "name": "content-disposition",
      "version": "0.5.4",
      "purl": "pkg:npm/content-disposition@0.5.4",
      "properties": [
        {
          "name": "amazon:inspector:sbom_generator:source_path",
          "value": "/home/ec2-user/simple-node-app/node_modules/content-disposition/package.json"
        }
      ]
    },
    {
      "bom-ref": "comp-40",
      "type": "library",
      "name": "braces",
      "version": "3.0.3",
      "purl": "pkg:npm/braces@3.0.3",
      "properties": [
        {
          "name": "amazon:inspector:sbom_generator:source_path",
          "value": "/home/ec2-user/simple-node-app/node_modules/braces/package.json"
        }
      ]
    },
    {
      "bom-ref": "comp-41",
      "type": "library",
      "name": "supports-color",
      "version": "5.5.0",
      "purl": "pkg:npm/supports-color@5.5.0",
      "properties": [
        {
          "name": "amazon:inspector:sbom_generator:source_path",
          "value": "/home/ec2-user/simple-node-app/node_modules/supports-color/package.json"
        }
      ]
    },
    {
      "bom-ref": "comp-42",
      "type": "library",
      "name": "utils-merge",
      "version": "1.0.1",
      "purl": "pkg:npm/utils-merge@1.0.1",
      "properties": [
        {
          "name": "amazon:inspector:sbom_generator:source_path",
          "value": "/home/ec2-user/simple-node-app/node_modules/utils-merge/package.json"
        }
      ]
    },
    {
      "bom-ref": "comp-43",
      "type": "library",
      "name": "proxy-addr",
      "version": "2.0.7",
      "purl": "pkg:npm/proxy-addr@2.0.7",
      "properties": [
        {
          "name": "amazon:inspector:sbom_generator:source_path",
          "value": "/home/ec2-user/simple-node-app/node_modules/proxy-addr/package.json"
        }
      ]
    },
    {
      "bom-ref": "comp-44",
      "type": "library",
      "name": "finalhandler",
      "version": "1.3.1",
      "purl": "pkg:npm/finalhandler@1.3.1",
      "properties": [
        {
          "name": "amazon:inspector:sbom_generator:source_path",
          "value": "/home/ec2-user/simple-node-app/node_modules/finalhandler/package.json"
        }
      ]
    },
    {
      "bom-ref": "comp-45",
      "type": "library",
      "name": "etag",
      "version": "1.8.1",
      "purl": "pkg:npm/etag@1.8.1",
      "properties": [
        {
          "name": "amazon:inspector:sbom_generator:source_path",
          "value": "/home/ec2-user/simple-node-app/node_modules/etag/package.json"
        }
      ]
    },
    {
      "bom-ref": "comp-46",
      "type": "library",
      "name": "path-to-regexp",
      "version": "0.1.12",
      "purl": "pkg:npm/path-to-regexp@0.1.12",
      "properties": [
        {
          "name": "amazon:inspector:sbom_generator:source_path",
          "value": "/home/ec2-user/simple-node-app/node_modules/path-to-regexp/package.json"
        }
      ]
    },
    {
      "bom-ref": "comp-47",
      "type": "library",
      "name": "call-bind-apply-helpers",
      "version": "1.0.2",
      "purl": "pkg:npm/call-bind-apply-helpers@1.0.2",
      "properties": [
        {
          "name": "amazon:inspector:sbom_generator:source_path",
          "value": "/home/ec2-user/simple-node-app/node_modules/call-bind-apply-helpers/package.json"
        }
      ]
    },
    {
      "bom-ref": "comp-48",
      "type": "library",
      "name": "balanced-match",
      "version": "1.0.2",
      "purl": "pkg:npm/balanced-match@1.0.2",
      "properties": [
        {
          "name": "amazon:inspector:sbom_generator:source_path",
          "value": "/home/ec2-user/simple-node-app/node_modules/balanced-match/package.json"
        }
      ]
    },
    {
      "bom-ref": "comp-49",
      "type": "library",
      "name": "merge-descriptors",
      "version": "1.0.3",
      "purl": "pkg:npm/merge-descriptors@1.0.3",
      "properties": [
        {
          "name": "amazon:inspector:sbom_generator:source_path",
          "value": "/home/ec2-user/simple-node-app/node_modules/merge-descriptors/package.json"
        }
      ]
    },
    {
      "bom-ref": "comp-50",
      "type": "library",
      "name": "call-bound",
      "version": "1.0.4",
      "purl": "pkg:npm/call-bound@1.0.4",
      "properties": [
        {
          "name": "amazon:inspector:sbom_generator:source_path",
          "value": "/home/ec2-user/simple-node-app/node_modules/call-bound/package.json"
        }
      ]
    },
    {
      "bom-ref": "comp-51",
      "type": "library",
      "name": "safe-buffer",
      "version": "5.2.1",
      "purl": "pkg:npm/safe-buffer@5.2.1",
      "properties": [
        {
          "name": "amazon:inspector:sbom_generator:source_path",
          "value": "/home/ec2-user/simple-node-app/node_modules/safe-buffer/package.json"
        }
      ]
    },
    {
      "bom-ref": "comp-52",
      "type": "library",
      "name": "is-extglob",
      "version": "2.1.1",
      "purl": "pkg:npm/is-extglob@2.1.1",
      "properties": [
        {
          "name": "amazon:inspector:sbom_generator:source_path",
          "value": "/home/ec2-user/simple-node-app/node_modules/is-extglob/package.json"
        }
      ]
    },
    {
      "bom-ref": "comp-53",
      "type": "library",
      "name": "to-regex-range",
      "version": "5.0.1",
      "purl": "pkg:npm/to-regex-range@5.0.1",
      "properties": [
        {
          "name": "amazon:inspector:sbom_generator:source_path",
          "value": "/home/ec2-user/simple-node-app/node_modules/to-regex-range/package.json"
        }
      ]
    },
    {
      "bom-ref": "comp-54",
      "type": "library",
      "name": "debug",
      "version": "2.6.9",
      "purl": "pkg:npm/debug@2.6.9",
      "properties": [
        {
          "name": "amazon:inspector:sbom_generator:source_path",
          "value": "/home/ec2-user/simple-node-app/node_modules/debug/package.json"
        }
      ]
    },
    {
      "bom-ref": "comp-55",
      "type": "library",
      "name": "normalize-path",
      "version": "3.0.0",
      "purl": "pkg:npm/normalize-path@3.0.0",
      "properties": [
        {
          "name": "amazon:inspector:sbom_generator:source_path",
          "value": "/home/ec2-user/simple-node-app/node_modules/normalize-path/package.json"
        }
      ]
    },
    {
      "bom-ref": "comp-56",
      "type": "library",
      "name": "semver",
      "version": "7.7.2",
      "purl": "pkg:npm/semver@7.7.2",
      "properties": [
        {
          "name": "amazon:inspector:sbom_generator:source_path",
          "value": "/home/ec2-user/simple-node-app/node_modules/semver/package.json"
        }
      ]
    },
    {
      "bom-ref": "comp-57",
      "type": "library",
      "name": "destroy",
      "version": "1.2.0",
      "purl": "pkg:npm/destroy@1.2.0",
      "properties": [
        {
          "name": "amazon:inspector:sbom_generator:source_path",
          "value": "/home/ec2-user/simple-node-app/node_modules/destroy/package.json"
        }
      ]
    },
    {
      "bom-ref": "comp-58",
      "type": "library",
      "name": "ee-first",
      "version": "1.1.1",
      "purl": "pkg:npm/ee-first@1.1.1",
      "properties": [
        {
          "name": "amazon:inspector:sbom_generator:source_path",
          "value": "/home/ec2-user/simple-node-app/node_modules/ee-first/package.json"
        }
      ]
    },
    {
      "bom-ref": "comp-59",
      "type": "library",
      "name": "statuses",
      "version": "2.0.1",
      "purl": "pkg:npm/statuses@2.0.1",
      "properties": [
        {
          "name": "amazon:inspector:sbom_generator:source_path",
          "value": "/home/ec2-user/simple-node-app/node_modules/statuses/package.json"
        }
      ]
    },
    {
      "bom-ref": "comp-60",
      "type": "library",
      "name": "glob-parent",
      "version": "5.1.2",
      "purl": "pkg:npm/glob-parent@5.1.2",
      "properties": [
        {
          "name": "amazon:inspector:sbom_generator:source_path",
          "value": "/home/ec2-user/simple-node-app/node_modules/glob-parent/package.json"
        }
      ]
    },
    {
      "bom-ref": "comp-61",
      "type": "library",
      "name": "get-proto",
      "version": "1.0.1",
      "purl": "pkg:npm/get-proto@1.0.1",
      "properties": [
        {
          "name": "amazon:inspector:sbom_generator:source_path",
          "value": "/home/ec2-user/simple-node-app/node_modules/get-proto/package.json"
        }
      ]
    },
    {
      "bom-ref": "comp-62",
      "type": "library",
      "name": "mime-types",
      "version": "2.1.35",
      "purl": "pkg:npm/mime-types@2.1.35",
      "properties": [
        {
          "name": "amazon:inspector:sbom_generator:source_path",
          "value": "/home/ec2-user/simple-node-app/node_modules/mime-types/package.json"
        }
      ]
    },
    {
      "bom-ref": "comp-63",
      "type": "library",
      "name": "has-flag",
      "version": "3.0.0",
      "purl": "pkg:npm/has-flag@3.0.0",
      "properties": [
        {
          "name": "amazon:inspector:sbom_generator:source_path",
          "value": "/home/ec2-user/simple-node-app/node_modules/has-flag/package.json"
        }
      ]
    },
    {
      "bom-ref": "comp-64",
      "type": "library",
      "name": "raw-body",
      "version": "2.5.2",
      "purl": "pkg:npm/raw-body@2.5.2",
      "properties": [
        {
          "name": "amazon:inspector:sbom_generator:source_path",
          "value": "/home/ec2-user/simple-node-app/node_modules/raw-body/package.json"
        }
      ]
    },
    {
      "bom-ref": "comp-65",
      "type": "library",
      "name": "es-define-property",
      "version": "1.0.1",
      "purl": "pkg:npm/es-define-property@1.0.1",
      "properties": [
        {
          "name": "amazon:inspector:sbom_generator:source_path",
          "value": "/home/ec2-user/simple-node-app/node_modules/es-define-property/package.json"
        }
      ]
    },
    {
      "bom-ref": "comp-66",
      "type": "library",
      "name": "has-symbols",
      "version": "1.1.0",
      "purl": "pkg:npm/has-symbols@1.1.0",
      "properties": [
        {
          "name": "amazon:inspector:sbom_generator:source_path",
          "value": "/home/ec2-user/simple-node-app/node_modules/has-symbols/package.json"
        }
      ]
    },
    {
      "bom-ref": "comp-67",
      "type": "library",
      "name": "media-typer",
      "version": "0.3.0",
      "purl": "pkg:npm/media-typer@0.3.0",
      "properties": [
        {
          "name": "amazon:inspector:sbom_generator:source_path",
          "value": "/home/ec2-user/simple-node-app/node_modules/media-typer/package.json"
        }
      ]
    },
    {
      "bom-ref": "comp-68",
      "type": "library",
      "name": "iconv-lite",
      "version": "0.4.24",
      "purl": "pkg:npm/iconv-lite@0.4.24",
      "properties": [
        {
          "name": "amazon:inspector:sbom_generator:source_path",
          "value": "/home/ec2-user/simple-node-app/node_modules/iconv-lite/package.json"
        }
      ]
    },
    {
      "bom-ref": "comp-69",
      "type": "library",
      "name": "cookie-signature",
      "version": "1.0.6",
      "purl": "pkg:npm/cookie-signature@1.0.6",
      "properties": [
        {
          "name": "amazon:inspector:sbom_generator:source_path",
          "value": "/home/ec2-user/simple-node-app/node_modules/cookie-signature/package.json"
        }
      ]
    },
    {
      "bom-ref": "comp-70",
      "type": "library",
      "name": "is-binary-path",
      "version": "2.1.0",
      "purl": "pkg:npm/is-binary-path@2.1.0",
      "properties": [
        {
          "name": "amazon:inspector:sbom_generator:source_path",
          "value": "/home/ec2-user/simple-node-app/node_modules/is-binary-path/package.json"
        }
      ]
    },
    {
      "bom-ref": "comp-71",
      "type": "library",
      "name": "get-intrinsic",
      "version": "1.3.0",
      "purl": "pkg:npm/get-intrinsic@1.3.0",
      "properties": [
        {
          "name": "amazon:inspector:sbom_generator:source_path",
          "value": "/home/ec2-user/simple-node-app/node_modules/get-intrinsic/package.json"
        }
      ]
    },
    {
      "bom-ref": "comp-72",
      "type": "library",
      "name": "ms",
      "version": "2.1.3",
      "purl": "pkg:npm/ms@2.1.3",
      "properties": [
        {
          "name": "amazon:inspector:sbom_generator:source_path",
          "value": "/home/ec2-user/simple-node-app/node_modules/send/node_modules/ms/package.json"
        }
      ]
    },
    {
      "bom-ref": "comp-73",
      "type": "library",
      "name": "brace-expansion",
      "version": "1.1.12",
      "purl": "pkg:npm/brace-expansion@1.1.12",
      "properties": [
        {
          "name": "amazon:inspector:sbom_generator:source_path",
          "value": "/home/ec2-user/simple-node-app/node_modules/brace-expansion/package.json"
        }
      ]
    },
    {
      "bom-ref": "comp-74",
      "type": "library",
      "name": "mime",
      "version": "1.6.0",
      "purl": "pkg:npm/mime@1.6.0",
      "properties": [
        {
          "name": "amazon:inspector:sbom_generator:source_path",
          "value": "/home/ec2-user/simple-node-app/node_modules/mime/package.json"
        }
      ]
    },
    {
      "bom-ref": "comp-75",
      "type": "library",
      "name": "concat-map",
      "version": "0.0.1",
      "purl": "pkg:npm/concat-map@0.0.1",
      "properties": [
        {
          "name": "amazon:inspector:sbom_generator:source_path",
          "value": "/home/ec2-user/simple-node-app/node_modules/concat-map/package.json"
        }
      ]
    },
    {
      "bom-ref": "comp-76",
      "type": "library",
      "name": "negotiator",
      "version": "0.6.3",
      "purl": "pkg:npm/negotiator@0.6.3",
      "properties": [
        {
          "name": "amazon:inspector:sbom_generator:source_path",
          "value": "/home/ec2-user/simple-node-app/node_modules/negotiator/package.json"
        }
      ]
    },
    {
      "bom-ref": "comp-77",
      "type": "library",
      "name": "anymatch",
      "version": "3.1.3",
      "purl": "pkg:npm/anymatch@3.1.3",
      "properties": [
        {
          "name": "amazon:inspector:sbom_generator:source_path",
          "value": "/home/ec2-user/simple-node-app/node_modules/anymatch/package.json"
        }
      ]
    },
    {
      "bom-ref": "comp-78",
      "type": "library",
      "name": "forwarded",
      "version": "0.2.0",
      "purl": "pkg:npm/forwarded@0.2.0",
      "properties": [
        {
          "name": "amazon:inspector:sbom_generator:source_path",
          "value": "/home/ec2-user/simple-node-app/node_modules/forwarded/package.json"
        }
      ]
    },
    {
      "bom-ref": "comp-79",
      "type": "library",
      "name": "vary",
      "version": "1.1.2",
      "purl": "pkg:npm/vary@1.1.2",
      "properties": [
        {
          "name": "amazon:inspector:sbom_generator:source_path",
          "value": "/home/ec2-user/simple-node-app/node_modules/vary/package.json"
        }
      ]
    },
    {
      "bom-ref": "comp-80",
      "type": "library",
      "name": "touch",
      "version": "3.1.1",
      "purl": "pkg:npm/touch@3.1.1",
      "properties": [
        {
          "name": "amazon:inspector:sbom_generator:source_path",
          "value": "/home/ec2-user/simple-node-app/node_modules/touch/package.json"
        }
      ]
    },
    {
      "bom-ref": "comp-81",
      "type": "library",
      "name": "parseurl",
      "version": "1.3.3",
      "purl": "pkg:npm/parseurl@1.3.3",
      "properties": [
        {
          "name": "amazon:inspector:sbom_generator:source_path",
          "value": "/home/ec2-user/simple-node-app/node_modules/parseurl/package.json"
        }
      ]
    },
    {
      "bom-ref": "comp-82",
      "type": "library",
      "name": "function-bind",
      "version": "1.1.2",
      "purl": "pkg:npm/function-bind@1.1.2",
      "properties": [
        {
          "name": "amazon:inspector:sbom_generator:source_path",
          "value": "/home/ec2-user/simple-node-app/node_modules/function-bind/package.json"
        }
      ]
    },
    {
      "bom-ref": "comp-83",
      "type": "library",
      "name": "setprototypeof",
      "version": "1.2.0",
      "purl": "pkg:npm/setprototypeof@1.2.0",
      "properties": [
        {
          "name": "amazon:inspector:sbom_generator:source_path",
          "value": "/home/ec2-user/simple-node-app/node_modules/setprototypeof/package.json"
        }
      ]
    },
    {
      "bom-ref": "comp-84",
      "type": "library",
      "name": "undefsafe",
      "version": "2.0.5",
      "purl": "pkg:npm/undefsafe@2.0.5",
      "properties": [
        {
          "name": "amazon:inspector:sbom_generator:source_path",
          "value": "/home/ec2-user/simple-node-app/node_modules/undefsafe/package.json"
        }
      ]
    },
    {
      "bom-ref": "comp-85",
      "type": "library",
      "name": "fresh",
      "version": "0.5.2",
      "purl": "pkg:npm/fresh@0.5.2",
      "properties": [
        {
          "name": "amazon:inspector:sbom_generator:source_path",
          "value": "/home/ec2-user/simple-node-app/node_modules/fresh/package.json"
        }
      ]
    },
    {
      "bom-ref": "comp-86",
      "type": "library",
      "name": "math-intrinsics",
      "version": "1.1.0",
      "purl": "pkg:npm/math-intrinsics@1.1.0",
      "properties": [
        {
          "name": "amazon:inspector:sbom_generator:source_path",
          "value": "/home/ec2-user/simple-node-app/node_modules/math-intrinsics/package.json"
        }
      ]
    },
    {
      "bom-ref": "comp-87",
      "type": "library",
      "name": "type-is",
      "version": "1.6.18",
      "purl": "pkg:npm/type-is@1.6.18",
      "properties": [
        {
          "name": "amazon:inspector:sbom_generator:source_path",
          "value": "/home/ec2-user/simple-node-app/node_modules/type-is/package.json"
        }
      ]
    },
    {
      "bom-ref": "comp-88",
      "type": "library",
      "name": "fill-range",
      "version": "7.1.1",
      "purl": "pkg:npm/fill-range@7.1.1",
      "properties": [
        {
          "name": "amazon:inspector:sbom_generator:source_path",
          "value": "/home/ec2-user/simple-node-app/node_modules/fill-range/package.json"
        }
      ]
    },
    {
      "bom-ref": "comp-89",
      "type": "library",
      "name": "express",
      "version": "4.21.2",
      "purl": "pkg:npm/express@4.21.2",
      "properties": [
        {
          "name": "amazon:inspector:sbom_generator:source_path",
          "value": "/home/ec2-user/simple-node-app/node_modules/express/package.json"
        }
      ]
    },
    {
      "bom-ref": "comp-90",
      "type": "library",
      "name": "side-channel-list",
      "version": "1.0.0",
      "purl": "pkg:npm/side-channel-list@1.0.0",
      "properties": [
        {
          "name": "amazon:inspector:sbom_generator:source_path",
          "value": "/home/ec2-user/simple-node-app/node_modules/side-channel-list/package.json"
        }
      ]
    },
    {
      "bom-ref": "comp-91",
      "type": "library",
      "name": "encodeurl",
      "version": "1.0.2",
      "purl": "pkg:npm/encodeurl@1.0.2",
      "properties": [
        {
          "name": "amazon:inspector:sbom_generator:source_path",
          "value": "/home/ec2-user/simple-node-app/node_modules/send/node_modules/encodeurl/package.json"
        }
      ]
    },
    {
      "bom-ref": "comp-92",
      "type": "library",
      "name": "dunder-proto",
      "version": "1.0.1",
      "purl": "pkg:npm/dunder-proto@1.0.1",
      "properties": [
        {
          "name": "amazon:inspector:sbom_generator:source_path",
          "value": "/home/ec2-user/simple-node-app/node_modules/dunder-proto/package.json"
        }
      ]
    },
    {
      "bom-ref": "comp-93",
      "type": "library",
      "name": "ignore-by-default",
      "version": "1.0.1",
      "purl": "pkg:npm/ignore-by-default@1.0.1",
      "properties": [
        {
          "name": "amazon:inspector:sbom_generator:source_path",
          "value": "/home/ec2-user/simple-node-app/node_modules/ignore-by-default/package.json"
        }
      ]
    },
    {
      "bom-ref": "comp-94",
      "type": "library",
      "name": "simple-update-notifier",
      "version": "2.0.0",
      "purl": "pkg:npm/simple-update-notifier@2.0.0",
      "properties": [
        {
          "name": "amazon:inspector:sbom_generator:source_path",
          "value": "/home/ec2-user/simple-node-app/node_modules/simple-update-notifier/package.json"
        }
      ]
    },
    {
      "bom-ref": "comp-95",
      "type": "library",
      "name": "cookie",
      "version": "0.7.1",
      "purl": "pkg:npm/cookie@0.7.1",
      "properties": [
        {
          "name": "amazon:inspector:sbom_generator:source_path",
          "value": "/home/ec2-user/simple-node-app/node_modules/cookie/package.json"
        }
      ]
    },
    {
      "bom-ref": "comp-96",
      "type": "library",
      "name": "unpipe",
      "version": "1.0.0",
      "purl": "pkg:npm/unpipe@1.0.0",
      "properties": [
        {
          "name": "amazon:inspector:sbom_generator:source_path",
          "value": "/home/ec2-user/simple-node-app/node_modules/unpipe/package.json"
        }
      ]
    },
    {
      "bom-ref": "comp-97",
      "type": "library",
      "name": "serve-static",
      "version": "1.16.2",
      "purl": "pkg:npm/serve-static@1.16.2",
      "properties": [
        {
          "name": "amazon:inspector:sbom_generator:source_path",
          "value": "/home/ec2-user/simple-node-app/node_modules/serve-static/package.json"
        }
      ]
    },
    {
      "bom-ref": "comp-98",
      "type": "library",
      "name": "debug",
      "version": "4.4.1",
      "purl": "pkg:npm/debug@4.4.1",
      "properties": [
        {
          "name": "amazon:inspector:sbom_generator:source_path",
          "value": "/home/ec2-user/simple-node-app/node_modules/nodemon/node_modules/debug/package.json"
        }
      ]
    },
    {
      "bom-ref": "comp-99",
      "type": "library",
      "name": "ms",
      "version": "2.1.3",
      "purl": "pkg:npm/ms@2.1.3",
      "properties": [
        {
          "name": "amazon:inspector:sbom_generator:source_path",
          "value": "/home/ec2-user/simple-node-app/node_modules/nodemon/node_modules/ms/package.json"
        }
      ]
    }
  ]
}
